LICENSE
MANIFEST.in
README.md
requirements.txt
setup.cfg
setup.py
jamstack/__init__.py
jamstack/__main__.py
jamstack.egg-info/PKG-INFO
jamstack.egg-info/SOURCES.txt
jamstack.egg-info/dependency_links.txt
jamstack.egg-info/entry_points.txt
jamstack.egg-info/requires.txt
jamstack.egg-info/top_level.txt
jamstack/__pycache__/__init__.cpython-38.pyc
jamstack/__pycache__/__main__.cpython-38.pyc
jamstack/api/file.py
jamstack/api/template.py
jamstack/api/__pycache__/file.cpython-38.pyc
jamstack/api/__pycache__/template.cpython-38.pyc
jamstack/jamdo/jamdo.py
jamstack/jamdo/__pycache__/jamdo.cpython-38.pyc
jamstack/sites/html5up/massively/info.json
jamstack/sites/html5up/massively/settings.py
jamstack/sites/html5up/massively/static.py
jamstack/sites/html5up/massively/templates/index.html
jamstack/sites/html5up/massively/templates/index2.html
jamstack/sites/html5up/massively/templates/index3.html
jamstack/sites/html5up/massively/templates/sections/bottom_scripts.html
jamstack/sites/html5up/massively/templates/sections/footer.html
jamstack/sites/html5up/massively/templates/sections/head_content.html
jamstack/sites/html5up/massively/templates/sections/main.html
jamstack/sites/html5up/massively/templates/sections/nav.html
jamstack/sites/html5up/phantom/info.json
jamstack/sites/html5up/phantom/posts.json
jamstack/sites/html5up/phantom/settings.py
jamstack/sites/html5up/phantom/static.py
jamstack/sites/html5up/phantom/templates/elements.html
jamstack/sites/html5up/phantom/templates/generic.html
jamstack/sites/html5up/phantom/templates/index.html
jamstack/sites/html5up/phantom/templates/post_template.html
jamstack/sites/html5up/phantom/templates/sections/bottom_scripts.html
jamstack/sites/html5up/phantom/templates/sections/footer.html
jamstack/sites/html5up/phantom/templates/sections/head_content.html
jamstack/sites/plain/info.json
jamstack/sites/plain/settings.py
jamstack/sites/plain/static.py
jamstack/sites/plain/templates/index.html
jamstack/sites/plain/templates/sections/body.html
jamstack/sites/plain/templates/sections/head.html