Metadata-Version: 2.1
Name: jamstack
Version: 1.1.0
Summary: Jamstack in Python
Home-page: https://github.com/jamstackpy/jamstack
Author: Abdur-Rahmaan Janhangeer
Author-email: arj.python@gmail.com
Project-URL: Bug Reports, https://github.com/jamstackpy/jamstack/issues
Project-URL: Source, https://github.com/jamstackpy/jamstack
Keywords: jamstack static website jinja2
Classifier: Development Status :: 5 - Production/Stable
Classifier: Intended Audience :: Developers
Classifier: License :: OSI Approved :: MIT License
Classifier: Programming Language :: Python :: 3.6
Classifier: Programming Language :: Python :: 3.7
Classifier: Programming Language :: Python :: 3.8
Classifier: Programming Language :: Python :: 3.9
Requires-Python: >=3.6
License-File: LICENSE
